pisugar/__init__.py
pisugar/pisugar.py
pisugar-0.1.0.dist-info/LICENSE
pisugar-0.1.0.dist-info/METADATA
pisugar-0.1.0.dist-info/WHEEL
pisugar-0.1.0.dist-info/top_level.txt
pisugar-0.1.0.dist-info/RECORD
